paperead/__init__.py
paperead/__main__.py
paperead/env.py
paperead/fsutils.py
paperead/repository/__init__.py
paperead/repository/materials.py
paperead/repository/notes.py
paperead/repository/schema.py
paperead/server/__init__.py
paperead/server/__main__.py
paperead/server/entrypoint.py
paperead/server/frontend.py
paperead/server/api/__init__.py
paperead/server/api/materials.py
paperead/server/api/notes.py
paperead/server/static/__init__.py
paperead/server/static/__main__.py
paperead/server/static/netlify/netlify.toml
paperead/server/wwwroot/build.json
paperead/server/wwwroot/favicon.ico
paperead/server/wwwroot/index.html
paperead/server/wwwroot/assets/index.a1a629bc.js
paperead/server/wwwroot/assets/index.f78add1d.css
paperead/server/wwwroot/static/css/APlayer.min.css
paperead/server/wwwroot/static/css/github-markdown.min.css
paperead/server/wwwroot/static/css/highlight-black.min.css
paperead/server/wwwroot/static/css/highlight-white.min.css
paperead/server/wwwroot/static/css/reveal-black.min.css
paperead/server/wwwroot/static/css/reveal-white.min.css
paperead-0.2.6.dist-info/METADATA
paperead-0.2.6.dist-info/WHEEL
paperead-0.2.6.dist-info/entry_points.txt
paperead-0.2.6.dist-info/top_level.txt
paperead-0.2.6.dist-info/RECORD
