Metadata-Version: 2.1
Name: paperead
Version: 0.2.6
Summary: A tiny tool to present and manage your reading and notes.
Home-page: https://github.com/StardustDL/paperead
Author: StardustDL
Author-email: stardustdl@163.com
License: UNKNOWN
Project-URL: Source Code, https://github.com/StardustDL/paperead
Project-URL: Changes, https://github.com/StardustDL/paperead/releases
Project-URL: Documentation, https://github.com/StardustDL/paperead
Project-URL: Bug Tracker, https://github.com/StardustDL/paperead/issues
Platform: UNKNOWN
Classifier: License :: OSI Approved :: Mozilla Public License 2.0 (MPL 2.0)
Classifier: Operating System :: OS Independent
Classifier: Programming Language :: Python :: 3
Classifier: Programming Language :: Python :: 3.7
Classifier: Programming Language :: Python :: 3.8
Classifier: Programming Language :: Python :: 3.9
Classifier: Programming Language :: Python :: 3.10
Classifier: Programming Language :: Python :: Implementation :: CPython
Classifier: Topic :: Utilities
Requires-Python: >=3.7
Requires-Dist: click (>=8.1.3)
Requires-Dist: Flask (>=2.1.2)
Requires-Dist: flask-cors (>=3.0.10)
Requires-Dist: Flask-BasicAuth (>=0.2.0)
Requires-Dist: PyYaml (>=6.0)
Requires-Dist: python-dateutil (>=2.8.2)
Requires-Dist: tornado (>=6.1)
Requires-Dist: marko (>=1.2.0)
